{
  "name": "PM Brief Generator — Slack → Agent → Notion + Reply",
  "nodes": [
    {
      "parameters": {
        "httpMethod": "POST",
        "path": "pm-brief",
        "options": {}
      },
      "id": "webhook-trigger",
      "name": "Webhook (Slack Event)",
      "type": "n8n-nodes-base.webhook",
      "typeVersion": 1,
      "position": [240, 300],
      "webhookId": "pm-brief-webhook",
      "notes": "Replace with Slack trigger node after connecting Slack OAuth. Set event to 'message' in a specific channel."
    },
    {
      "parameters": {
        "jsCode": "// Extract the text from the Slack event payload\n// Adjust field paths if using native Slack trigger vs webhook\nconst body = $input.first().json.body || $input.first().json;\nconst text = body.event?.text || body.text || body.raw_input || 'No input found';\nconst channel = body.event?.channel || body.channel || 'unknown';\nconst user = body.event?.user || body.user || 'unknown';\n\nreturn [{\n  json: {\n    raw_input: text,\n    channel,\n    user,\n    timestamp: new Date().toISOString()\n  }\n}];"
      },
      "id": "extract-text",
      "name": "Extract Slack Text",
      "type": "n8n-nodes-base.code",
      "typeVersion": 2,
      "position": [460, 300]
    },
    {
      "parameters": {
        "method": "POST",
        "url": "http://localhost:8080/brief",
        "sendBody": true,
        "specifyBody": "json",
        "jsonBody": "={{ { \"raw_input\": $json.raw_input } }}",
        "options": {
          "timeout": 30000
        }
      },
      "id": "call-agent",
      "name": "Call Brief Generator Agent",
      "type": "n8n-nodes-base.httpRequest",
      "typeVersion": 4,
      "position": [680, 300],
      "notes": "IMPORTANT: Replace URL with your actual agent endpoint. For local testing, run: python agent_http.py (see README). For production, deploy agent to Render/Railway/Fly.io and use that URL."
    },
    {
      "parameters": {
        "jsCode": "// Parse and validate the agent response\nconst raw = $input.first().json;\n\n// Handle both direct JSON response and nested response.body\nlet brief;\ntry {\n  brief = typeof raw === 'string' ? JSON.parse(raw) : raw;\n} catch(e) {\n  return [{ json: { error: 'Failed to parse agent response', raw } }];\n}\n\n// Validate required fields\nconst required = ['problem', 'affected', 'metrics', 'assumption'];\nconst missing = required.filter(k => !brief[k]);\nif (missing.length > 0) {\n  return [{ json: { error: `Missing fields: ${missing.join(', ')}`, brief } }];\n}\n\n// Format for downstream nodes\nreturn [{\n  json: {\n    ...brief,\n    metrics_formatted: Array.isArray(brief.metrics) \n      ? brief.metrics.join('\\n• ') \n      : brief.metrics,\n    is_valid: true\n  }\n}];"
      },
      "id": "parse-validate",
      "name": "Parse + Validate Brief",
      "type": "n8n-nodes-base.code",
      "typeVersion": 2,
      "position": [900, 300]
    },
    {
      "parameters": {
        "resource": "page",
        "operation": "create",
        "databaseId": "YOUR_NOTION_DATABASE_ID",
        "title": "={{ 'PM Brief: ' + $json.problem.substring(0, 80) }}",
        "propertiesUi": {
          "propertyValues": [
            {
              "key": "Status",
              "type": "select",
              "selectValue": "Draft"
            },
            {
              "key": "Created",
              "type": "date",
              "dateValue": "={{ $now }}"
            }
          ]
        },
        "blockUi": {
          "blockValues": [
            {
              "type": "heading_2",
              "textContent": "Problem"
            },
            {
              "type": "paragraph",
              "textContent": "={{ $json.problem }}"
            },
            {
              "type": "heading_2",
              "textContent": "Who's Affected"
            },
            {
              "type": "paragraph",
              "textContent": "={{ $json.affected }}"
            },
            {
              "type": "heading_2",
              "textContent": "Success Metrics"
            },
            {
              "type": "bulleted_list_item",
              "textContent": "={{ $json.metrics[0] }}"
            },
            {
              "type": "bulleted_list_item",
              "textContent": "={{ $json.metrics[1] }}"
            },
            {
              "type": "heading_2",
              "textContent": "Key Assumption to Validate"
            },
            {
              "type": "paragraph",
              "textContent": "={{ $json.assumption }}"
            },
            {
              "type": "heading_2",
              "textContent": "Confidence"
            },
            {
              "type": "paragraph",
              "textContent": "={{ $json.confidence || 'not set' }}"
            }
          ]
        }
      },
      "id": "create-notion-page",
      "name": "Create Notion Page",
      "type": "n8n-nodes-base.notion",
      "typeVersion": 2,
      "position": [1120, 200],
      "notes": "Set YOUR_NOTION_DATABASE_ID to your briefs database ID. Connect Notion credentials in n8n Settings > Credentials."
    },
    {
      "parameters": {
        "channel": "={{ $('Extract Slack Text').first().json.channel }}",
        "text": "=✅ *Brief generated* → <{{ $json.url }}|View in Notion>\n\n*Problem:* {{ $('Parse + Validate Brief').first().json.problem }}\n*Assumption to validate:* {{ $('Parse + Validate Brief').first().json.assumption }}",
        "otherOptions": {}
      },
      "id": "slack-reply",
      "name": "Reply in Slack",
      "type": "n8n-nodes-base.slack",
      "typeVersion": 2,
      "position": [1120, 400],
      "notes": "Connect Slack credentials. This replies in the same channel the message came from."
    }
  ],
  "connections": {
    "Webhook (Slack Event)": {
      "main": [[ { "node": "Extract Slack Text", "type": "main", "index": 0 } ]]
    },
    "Extract Slack Text": {
      "main": [[ { "node": "Call Brief Generator Agent", "type": "main", "index": 0 } ]]
    },
    "Call Brief Generator Agent": {
      "main": [[ { "node": "Parse + Validate Brief", "type": "main", "index": 0 } ]]
    },
    "Parse + Validate Brief": {
      "main": [[
        { "node": "Create Notion Page", "type": "main", "index": 0 },
        { "node": "Reply in Slack", "type": "main", "index": 0 }
      ]]
    }
  },
  "settings": {
    "executionOrder": "v1"
  },
  "_workshop_notes": {
    "import_steps": [
      "1. Go to n8n.io/cloud and create a free account",
      "2. Create a new workflow",
      "3. Click the three-dot menu → Import from JSON → paste this file",
      "4. Set credentials: Slack OAuth app, Notion integration, your agent HTTP endpoint",
      "5. For local testing: run agent_http.py (included in repo) on port 8080",
      "6. Activate workflow → test by posting in your Slack test channel"
    ],
    "agent_endpoint_options": [
      "Local: python agent_http.py (runs on localhost:8080)",
      "Cloud: deploy to Render.com (free tier) — see README deploy section",
      "Cloud: Railway.app — $5/mo, simpler deploys"
    ]
  }
}
